{
  "latitude/longitude": "44.0833333 -124.1666667", 
  "features": "Beach", 
  "locality": "8.0 km N of Florence", 
  "url": "http://macaulaylibrary.org/audio/53", 
  "title": "Steller Sea Lion", 
  "recorders": "MAGNEMITE 610E", 
  "accessories": "Parabola 45.7cm/11.4cm (18in/4.5in)", 
  "channels": "Mono", 
  "equipment_note": "2-transistor pre-amp used. parabola 18.75/4.25; Copy recorder: Tapesonic 70-c, no filter, using tape Sony SLH550.", 
  "habitats": "Marine", 
  "geography": "United States Oregon"
}