{
  "latitude/longitude": "-6.1565833 50.3438333", 
  "elevation": "380 meters", 
  "locality": "Floresta Nacional de Carajas; Aguas Claras Road (clearing at beginning of road)", 
  "url": "http://macaulaylibrary.org/audio/126745", 
  "title": "Buff-throated Woodcreeper (Dusky-billed)", 
  "recorders": "NAGRA ARES-BB+", 
  "accessories": "Roch\u00e9 Parabola 74cm/17.7cm (29.1in/7in)", 
  "channels": "Mono", 
  "equipment_note": "", 
  "habitats": "Evergreen Forest", 
  "geography": "Brazil Par\u00e1"
}